pugs/__init__.py
pugs/logic.py
pugs-0.0.1.dist-info/LICENSE.txt
pugs-0.0.1.dist-info/METADATA
pugs-0.0.1.dist-info/WHEEL
pugs-0.0.1.dist-info/top_level.txt
pugs-0.0.1.dist-info/zip-safe
pugs-0.0.1.dist-info/RECORD
