Metadata-Version: 2.1
Name: pugs
Version: 0.0.1
Summary: UNKNOWN
Home-page: https://github.com/gaborbernat/pugs
Author: Bernat Gabor
Maintainer: Bernat Gabor
Maintainer-email: gaborjbernat@gmail.com
License: UNKNOWN
Project-URL: Source, https://github.com/gaborbernat/pugs
Project-URL: Tracker, https://github.com/gaborbernat/pugs/issues
Keywords: pugs,packaging
Platform: any
Classifier: Development Status :: 5 - Production/Stable
Classifier: Intended Audience :: Developers
Classifier: License :: OSI Approved :: MIT License
Classifier: Programming Language :: Python :: 2
Classifier: Programming Language :: Python :: 2.7
Classifier: Programming Language :: Python :: 3
Classifier: Programming Language :: Python :: 3.4
Classifier: Programming Language :: Python :: 3.5
Classifier: Programming Language :: Python :: 3.6
Classifier: Programming Language :: Python :: 3.7
Requires-Python: >=2.7, !=3.0.*, !=3.1.*, !=3.2.*, !=3.3.*
Provides-Extra: test
Requires-Dist: pytest (<5,>=3.5.0) ; extra == 'test'
